psprint/__init__.py
psprint/__main__.py
psprint/ansi.py
psprint/ansi.yml
psprint/errors.py
psprint/mark_types.py
psprint/printer.py
psprint/style.yml
psprint/text_types.py
psprint-21.3.1.dist-info/LICENSE
psprint-21.3.1.dist-info/METADATA
psprint-21.3.1.dist-info/WHEEL
psprint-21.3.1.dist-info/top_level.txt
psprint-21.3.1.dist-info/RECORD
