Metadata-Version: 2.1
Name: psprint
Version: 21.3.1
Summary: psprint - Prompt String Print
Home-page: https://github.com/pradyparanjpe/psprint
Author: Pradyumna Paranjape
Author-email: pradyparanjpe@rediffmail.com
License: LGPLv3
Platform: linux
Requires-Python: >=3.7
Requires-Dist: pyyaml
